zlapi/__init__.py
zlapi/_aevents.py
zlapi/_client.py
zlapi/_core.py
zlapi/_exception.py
zlapi/_message.py
zlapi/_objects.py
zlapi/_package.py
zlapi/_parse_message.py
zlapi/_state.py
zlapi/_threads.py
zlapi/_util.py
zlapi/logging.py
zlapi/models.py
zlapi/Async/__init__.py
zlapi/Async/_async.py
zlapi/Async/_state.py
zlapi/simple/__init__.py
zlapi/simple/_async.py
zlapi-1.0.2.dist-info/LICENSE
zlapi-1.0.2.dist-info/METADATA
zlapi-1.0.2.dist-info/WHEEL
zlapi-1.0.2.dist-info/top_level.txt
zlapi-1.0.2.dist-info/RECORD
