Metadata-Version: 2.1
Name: zlapi
Version: 1.0.2
Summary: zlapi: Zalo API for Python
Author: Lê Quốc Việt (Vexx)
Author-email: <vrxxdev@gmail.com>
Keywords: python,zalo,api,zalo api,zalo chat,requests
Classifier: Development Status :: 3 - Alpha
Classifier: Intended Audience :: Developers
Classifier: License :: OSI Approved :: MIT License
Classifier: Operating System :: OS Independent
Classifier: Natural Language :: English
Classifier: Programming Language :: Python
Classifier: Programming Language :: Python :: 3
Classifier: Programming Language :: Python :: Implementation :: CPython
Classifier: Programming Language :: Python :: Implementation :: PyPy
Classifier: Topic :: Communications :: Chat
Classifier: Topic :: Internet :: WWW/HTTP
Classifier: Topic :: Internet :: WWW/HTTP :: Dynamic Content
Classifier: Topic :: Software Development :: Libraries
Classifier: Topic :: Software Development :: Libraries :: Python Modules
License-File: LICENSE
Requires-Dist: requests
Requires-Dist: aiohttp
Requires-Dist: aenum
Requires-Dist: attr
Requires-Dist: pycryptodome
Requires-Dist: datetime
Requires-Dist: munch
Requires-Dist: websockets
